StockTrainer.py
stocktrainer/__init__.py
stocktrainer/stocktrainer.py
stocktrainer-0.1.1.dist-info/LICENSE.rst
stocktrainer-0.1.1.dist-info/METADATA
stocktrainer-0.1.1.dist-info/WHEEL
stocktrainer-0.1.1.dist-info/top_level.txt
stocktrainer-0.1.1.dist-info/RECORD
