Metadata-Version: 2.1
Name: stocktrainer
Version: 0.1.1
Summary: Stock environment for training machine learning agents
Home-page: https://github.com/dasante78/StockTrainer
Author: Daniel Prakah-Asante
Author-email: doprakah@mit.edu
License: UNKNOWN
Keywords: USEFULL,STOCKS,MACHINE LEARNING,AI,ARTIFICAL INTELLIGENCE
Platform: UNKNOWN
Classifier: Development Status :: 3 - Alpha
Classifier: Intended Audience :: Developers
Classifier: Topic :: Software Development :: Build Tools
Classifier: Programming Language :: Python :: 3.5
Classifier: Programming Language :: Python :: 3.6
Classifier: Programming Language :: Python :: 3.7
Requires-Dist: pandas
Requires-Dist: numpy
Requires-Dist: datetime
Requires-Dist: pandas-datareader
Requires-Dist: yfinance
